tenets/__init__.py
tenets/__main__.py
tenets/config.py
tenets/cli/__init__.py
tenets/cli/__main__.py
tenets/cli/app.py
tenets/cli/commands/__init__.py
tenets/cli/commands/_utils.py
tenets/cli/commands/chronicle.py
tenets/cli/commands/config.py
tenets/cli/commands/distill.py
tenets/cli/commands/examine.py
tenets/cli/commands/instill.py
tenets/cli/commands/momentum.py
tenets/cli/commands/rank.py
tenets/cli/commands/session.py
tenets/cli/commands/system_instruction.py
tenets/cli/commands/tenet.py
tenets/cli/commands/viz.py
tenets/core/__init__.py
tenets/core/analysis/__init__.py
tenets/core/analysis/analyzer.py
tenets/core/analysis/base.py
tenets/core/analysis/project_detector.py
tenets/core/analysis/implementations/__init__.py
tenets/core/analysis/implementations/cpp_analyzer.py
tenets/core/analysis/implementations/csharp_analyzer.py
tenets/core/analysis/implementations/css_analyzer.py
tenets/core/analysis/implementations/dart_analyzer.py
tenets/core/analysis/implementations/gdscript_analyzer.py
tenets/core/analysis/implementations/generic_analyzer.py
tenets/core/analysis/implementations/go_analyzer.py
tenets/core/analysis/implementations/html_analyzer.py
tenets/core/analysis/implementations/java_analyzer.py
tenets/core/analysis/implementations/javascript_analyzer.py
tenets/core/analysis/implementations/kotlin_analyzer.py
tenets/core/analysis/implementations/php_analyzer.py
tenets/core/analysis/implementations/python_analyzer.py
tenets/core/analysis/implementations/ruby_analyzer.py
tenets/core/analysis/implementations/rust_analyzer.py
tenets/core/analysis/implementations/scala_analyzer.py
tenets/core/analysis/implementations/swift_analyzer.py
tenets/core/distiller/__init__.py
tenets/core/distiller/aggregator.py
tenets/core/distiller/distiller.py
tenets/core/distiller/formatter.py
tenets/core/distiller/optimizer.py
tenets/core/distiller/transform.py
tenets/core/examiner/__init__.py
tenets/core/examiner/complexity.py
tenets/core/examiner/examiner.py
tenets-0.10.0.dist-info/METADATA
tenets-0.10.0.dist-info/WHEEL
tenets-0.10.0.dist-info/entry_points.txt
tenets-0.10.0.dist-info/licenses/LICENSE
tenets-0.10.0.dist-info/RECORD
