Metadata-Version: 2.4
Name: tenets
Version: 0.10.0
Summary: MCP server for AI coding assistants — intelligent code context via Model Context Protocol
Project-URL: Homepage, https://github.com/jddunn/tenets
Project-URL: Documentation, https://tenets.dev/docs
Project-URL: Repository, https://github.com/jddunn/tenets
Project-URL: Issues, https://github.com/jddunn/tenets/issues
Project-URL: Changelog, https://github.com/jddunn/tenets/blob/main/CHANGELOG.md
Author-email: Tenets Team <team@tenets.dev>
License: MIT
License-File: LICENSE
Keywords: ai,ai-coding-assistant,claude,code-analysis,context-management,cursor,developer-tools,llm,mcp,model-context-protocol,prompt-engineering
Classifier: Development Status :: 3 - Alpha
Classifier: Intended Audience :: Developers
Classifier: License :: OSI Approved :: MIT License
Classifier: Programming Language :: Python :: 3
Classifier: Programming Language :: Python :: 3.9
Classifier: Programming Language :: Python :: 3.10
Classifier: Programming Language :: Python :: 3.11
Classifier: Programming Language :: Python :: 3.12
Classifier: Programming Language :: Python :: 3.13
Classifier: Topic :: Scientific/Engineering :: Artificial Intelligence
Classifier: Topic :: Software Development :: Code Generators
Classifier: Topic :: Software Development :: Libraries :: Python Modules
Classifier: Topic :: Software Development :: Quality Assurance
Requires-Python: >=3.9
Requires-Dist: aiofiles>=23.0.0
Requires-Dist: chardet>=5.0.0
Requires-Dist: click>=8.1.0
Requires-Dist: gitpython>=3.1.0
Requires-Dist: httpx>=0.25.0
Requires-Dist: numpy>=1.24.0
Requires-Dist: pathspec>=0.11.0
Requires-Dist: psutil>=5.9.0
Requires-Dist: pydantic-settings>=2.0.0
Requires-Dist: pydantic>=2.0.0
Requires-Dist: pyyaml>=6.0
Requires-Dist: rich>=13.0.0
Requires-Dist: tqdm>=4.65.0
Requires-Dist: typer>=0.9.0
Provides-Extra: all
Requires-Dist: alembic>=1.12.0; extra == 'all'
Requires-Dist: anthropic>=0.25.0; extra == 'all'
Requires-Dist: diskcache>=5.6.0; extra == 'all'
Requires-Dist: faiss-cpu>=1.7.4; extra == 'all'
Requires-Dist: fastapi>=0.100.0; extra == 'all'
Requires-Dist: graphviz>=0.20.0; extra == 'all'
Requires-Dist: huggingface-hub>=0.19.0; extra == 'all'
Requires-Dist: jinja2>=3.1.0; extra == 'all'
Requires-Dist: litellm>=1.0.0; extra == 'all'
Requires-Dist: matplotlib>=3.7.0; extra == 'all'
Requires-Dist: mcp[cli]>=1.0.0; extra == 'all'
Requires-Dist: networkx>=3.0; extra == 'all'
Requires-Dist: nltk>=3.8.0; extra == 'all'
Requires-Dist: openai>=1.0.0; extra == 'all'
Requires-Dist: plotly>=5.0.0; extra == 'all'
Requires-Dist: pydot>=1.4.0; extra == 'all'
Requires-Dist: python-multipart>=0.0.6; extra == 'all'
Requires-Dist: rake-nltk>=1.0.6; extra == 'all'
Requires-Dist: redis>=5.0.0; extra == 'all'
Requires-Dist: scikit-learn>=1.3.0; extra == 'all'
Requires-Dist: sentence-transformers>=2.2.0; extra == 'all'
Requires-Dist: sqlalchemy>=2.0.0; extra == 'all'
Requires-Dist: sse-starlette>=1.6.0; extra == 'all'
Requires-Dist: textstat>=0.7.3; extra == 'all'
Requires-Dist: tiktoken>=0.5.0; extra == 'all'
Requires-Dist: torch>=2.0.0; extra == 'all'
Requires-Dist: transformers>=4.30.0; extra == 'all'
Requires-Dist: uvicorn>=0.23.0; extra == 'all'
Requires-Dist: uvicorn[standard]>=0.23.0; extra == 'all'
Requires-Dist: websockets>=11.0; extra == 'all'
Requires-Dist: yake>=0.4.8; extra == 'all'
Provides-Extra: db
Requires-Dist: alembic>=1.12.0; extra == 'db'
Requires-Dist: diskcache>=5.6.0; extra == 'db'
Requires-Dist: redis>=5.0.0; extra == 'db'
Requires-Dist: sqlalchemy>=2.0.0; extra == 'db'
Provides-Extra: dev
Requires-Dist: autoflake>=2.2.0; extra == 'dev'
Requires-Dist: bandit[toml]>=1.7.5; extra == 'dev'
Requires-Dist: black>=23.0.0; extra == 'dev'
Requires-Dist: build>=1.0.0; extra == 'dev'
Requires-Dist: commitizen>=3.12.0; extra == 'dev'
Requires-Dist: coverage-badge>=1.1.0; extra == 'dev'
Requires-Dist: coverage>=7.3.0; extra == 'dev'
Requires-Dist: faker>=19.0.0; extra == 'dev'
Requires-Dist: freezegun>=1.2.0; extra == 'dev'
Requires-Dist: hypothesis>=6.82.0; extra == 'dev'
Requires-Dist: isort>=5.12.0; extra == 'dev'
Requires-Dist: mike>=2.0.0; extra == 'dev'
Requires-Dist: mkdocs-autorefs>=1.0.0; extra == 'dev'
Requires-Dist: mkdocs-awesome-pages-plugin>=2.9.0; extra == 'dev'
Requires-Dist: mkdocs-gen-files>=0.5.0; extra == 'dev'
Requires-Dist: mkdocs-git-authors-plugin>=0.7.0; extra == 'dev'
Requires-Dist: mkdocs-git-revision-date-localized-plugin>=1.2.0; extra == 'dev'
Requires-Dist: mkdocs-jupyter>=0.24.0; extra == 'dev'
Requires-Dist: mkdocs-literate-nav>=0.6.0; extra == 'dev'
Requires-Dist: mkdocs-macros-plugin>=0.9.0; extra == 'dev'
Requires-Dist: mkdocs-material[imaging]>=9.5.0; extra == 'dev'
Requires-Dist: mkdocs-mermaid2-plugin>=1.1.0; extra == 'dev'
Requires-Dist: mkdocs-minify-plugin>=0.8.0; extra == 'dev'
Requires-Dist: mkdocs-section-index>=0.3.0; extra == 'dev'
Requires-Dist: mkdocs>=1.5.0; extra == 'dev'
Requires-Dist: mkdocstrings[python]>=0.24.0; extra == 'dev'
Requires-Dist: mypy>=1.5.0; extra == 'dev'
Requires-Dist: pip-tools>=7.3.0; extra == 'dev'
Requires-Dist: pre-commit>=3.4.0; extra == 'dev'
Requires-Dist: pyinstaller>=6.0.0; extra == 'dev'
Requires-Dist: pytest-asyncio>=0.21.0; extra == 'dev'
Requires-Dist: pytest-cov>=4.1.0; extra == 'dev'
Requires-Dist: pytest-mock>=3.12.0; extra == 'dev'
Requires-Dist: pytest-timeout>=2.2.0; extra == 'dev'
Requires-Dist: pytest-xdist>=3.3.0; extra == 'dev'
Requires-Dist: pytest>=7.4.0; extra == 'dev'
Requires-Dist: ruff>=0.1.0; extra == 'dev'
Requires-Dist: safety>=2.3.0; extra == 'dev'
Requires-Dist: twine>=4.0.0; extra == 'dev'
Requires-Dist: wheel>=0.41.0; extra == 'dev'
Provides-Extra: docs
Requires-Dist: mike>=2.0.0; extra == 'docs'
Requires-Dist: mkdocs-awesome-pages-plugin>=2.9.0; extra == 'docs'
Requires-Dist: mkdocs-gen-files>=0.5.0; extra == 'docs'
Requires-Dist: mkdocs-git-revision-date-localized-plugin>=1.2.0; extra == 'docs'
Requires-Dist: mkdocs-literate-nav>=0.6.0; extra == 'docs'
Requires-Dist: mkdocs-material[imaging]>=9.5.0; extra == 'docs'
Requires-Dist: mkdocs-minify-plugin>=0.7.0; extra == 'docs'
Requires-Dist: mkdocs-redirects>=1.2.0; extra == 'docs'
Requires-Dist: mkdocs-section-index>=0.3.0; extra == 'docs'
Requires-Dist: mkdocs>=1.5.0; extra == 'docs'
Requires-Dist: mkdocstrings[python]>=0.23.0; extra == 'docs'
Requires-Dist: pymdown-extensions>=10.0; extra == 'docs'
Provides-Extra: light
Requires-Dist: nltk>=3.8.0; extra == 'light'
Requires-Dist: rake-nltk>=1.0.6; extra == 'light'
Requires-Dist: scikit-learn>=1.3.0; extra == 'light'
Requires-Dist: textstat>=0.7.3; extra == 'light'
Requires-Dist: yake>=0.4.8; extra == 'light'
Provides-Extra: mcp
Requires-Dist: mcp[cli]>=1.0.0; extra == 'mcp'
Requires-Dist: nltk>=3.8.0; extra == 'mcp'
Requires-Dist: scikit-learn>=1.3.0; extra == 'mcp'
Requires-Dist: sse-starlette>=1.6.0; extra == 'mcp'
Requires-Dist: uvicorn>=0.23.0; extra == 'mcp'
Provides-Extra: ml
Requires-Dist: anthropic>=0.25.0; extra == 'ml'
Requires-Dist: faiss-cpu>=1.7.4; extra == 'ml'
Requires-Dist: huggingface-hub>=0.19.0; extra == 'ml'
Requires-Dist: litellm>=1.0.0; extra == 'ml'
Requires-Dist: openai>=1.0.0; extra == 'ml'
Requires-Dist: sentence-transformers>=2.2.0; extra == 'ml'
Requires-Dist: tiktoken>=0.5.0; extra == 'ml'
Requires-Dist: torch>=2.0.0; extra == 'ml'
Requires-Dist: transformers>=4.30.0; extra == 'ml'
Provides-Extra: test
Requires-Dist: faker>=20.0.0; extra == 'test'
Requires-Dist: hypothesis>=6.92.0; extra == 'test'
Requires-Dist: pytest-asyncio>=0.21.0; extra == 'test'
Requires-Dist: pytest-cov>=4.1.0; extra == 'test'
Requires-Dist: pytest-mock>=3.12.0; extra == 'test'
Requires-Dist: pytest-timeout>=2.2.0; extra == 'test'
Requires-Dist: pytest-xdist>=3.3.0; extra == 'test'
Requires-Dist: pytest>=7.4.0; extra == 'test'
Requires-Dist: responses>=0.24.0; extra == 'test'
Requires-Dist: tiktoken>=0.5.0; extra == 'test'
Provides-Extra: viz
Requires-Dist: graphviz>=0.20.0; extra == 'viz'
Requires-Dist: matplotlib>=3.7.0; extra == 'viz'
Requires-Dist: networkx>=3.0; extra == 'viz'
Requires-Dist: plotly>=5.0.0; extra == 'viz'
Requires-Dist: pydot>=1.4.0; extra == 'viz'
Provides-Extra: web
Requires-Dist: fastapi>=0.100.0; extra == 'web'
Requires-Dist: jinja2>=3.1.0; extra == 'web'
Requires-Dist: python-multipart>=0.0.6; extra == 'web'
Requires-Dist: sse-starlette>=1.6.0; extra == 'web'
Requires-Dist: uvicorn[standard]>=0.23.0; extra == 'web'
Requires-Dist: websockets>=11.0; extra == 'web'
